err_hunter/__init__.py
err_hunter/attr.py
err_hunter/frame_operations.py
err_hunter/myinspect.py
err_hunter/mylogger.py
err_hunter/mylogging.py
err_hunter/traceback2.py
err_hunter/third_party/__init__.py
err_hunter/third_party/colorama/__init__.py
err_hunter/third_party/colorama/ansi.py
err_hunter/third_party/colorama/ansitowin32.py
err_hunter/third_party/colorama/initialise.py
err_hunter/third_party/colorama/win32.py
err_hunter/third_party/colorama/winterm.py
err_hunter/third_party/logzero/__init__.py
err_hunter/third_party/logzero/colors.py
err_hunter-0.8.3.dist-info/METADATA
err_hunter-0.8.3.dist-info/WHEEL
err_hunter-0.8.3.dist-info/top_level.txt
err_hunter-0.8.3.dist-info/RECORD
