Metadata-Version: 2.1
Name: err-hunter
Version: 0.8.3
Summary: Enhanced traceback and logging utils
Home-page: https://github.com/aploium/my_utils/tree/master/err_hunter
Author: ap
Author-email: meow@meow.cat
Platform: any
Classifier: Operating System :: OS Independent
Classifier: Programming Language :: Python
Classifier: Programming Language :: Python :: 3.8
Classifier: Programming Language :: Python :: 3.9
Classifier: Programming Language :: Python :: 3.10
Classifier: Programming Language :: Python :: 3.11
Classifier: Programming Language :: Python :: 3.12
Classifier: Programming Language :: Python :: 3.13
